{"_id":"67da3f5c4114b77b63ecbac0","id":"sshao0516/CrowdHuman","author":"sshao0516","sha":"d97203da87e348ea69f7a7633a57c21a956120a6","lastModified":"2025-03-19T11:32:58.000Z","private":false,"gated":false,"disabled":false,"tags":["task_categories:object-detection","language:en","license:cc-by-nc-4.0","size_categories:10K<n<100K","modality:image","arxiv:1805.00123","region:us"],"description":"\n\t\n\t\t\n\t\n\t\n\t\tCrowdHuman: A Benchmark for Detecting Human in a Crowd\n\t\n\n\n🏠 homepage: https://www.crowdhuman.org/\n📄 paper: https://arxiv.org/pdf/1805.00123\n\nCrowdHuman is a benchmark dataset to better evaluate detectors in crowd scenarios. The CrowdHuman dataset is large, rich-annotated and contains high diversity. CrowdHuman contains 15000, 4370 and 5000 images for training, validation, and testing, respectively. There are a total of 470K human instances from train and validation subsets and… See the full description on the dataset page: https://huggingface.co/datasets/sshao0516/CrowdHuman.","downloads":1958,"likes":12,"cardData":{"license":"cc-by-nc-4.0","task_categories":["object-detection"],"language":["en"],"pretty_name":"CrowdHuman","size_categories":["10K<n<100K"]},"siblings":[{"rfilename":".gitattributes"},{"rfilename":"CrowdHuman_test.zip"},{"rfilename":"CrowdHuman_train01.zip"},{"rfilename":"CrowdHuman_train02.zip"},{"rfilename":"CrowdHuman_train03.zip"},{"rfilename":"CrowdHuman_val.zip"},{"rfilename":"README.md"},{"rfilename":"annotation_train.odgt"},{"rfilename":"annotation_val.odgt"}],"createdAt":"2025-03-19T03:51:56.000Z","usedStorage":14220944187}